{
  "MORIMENS_CHARACTER_DOLL.aromaPrinciple": "[sine][blue]新的旅程，从一份干净模板开始。[/blue][/sine]",
  "MORIMENS_CHARACTER_DOLL.banter.alive.endTurnPing": "回合结束。",
  "MORIMENS_CHARACTER_DOLL.banter.dead.endTurnPing": "我先撤退。",
  "MORIMENS_CHARACTER_DOLL.cardsModifierDescription": "模板角色的卡牌现在会出现在奖励和商店中。",
  "MORIMENS_CHARACTER_DOLL.cardsModifierTitle": "模板卡牌",
  "MORIMENS_CHARACTER_DOLL.defeatMessage": "模板还需要继续调整。",
  "MORIMENS_CHARACTER_DOLL.description": "一个用于验证 RitsuLib 模板工程的示例角色。\n复制模板后，把这里替换成你的角色设定。",
  "MORIMENS_CHARACTER_DOLL.eventDeathPrevention": "模板角色继续坚持。",
  "MORIMENS_CHARACTER_DOLL.flavor": "一份干净的模板，等待被改造成新的冒险。",
  "MORIMENS_CHARACTER_DOLL.goldMonologue": "这些金币足够开始测试。",
  "MORIMENS_CHARACTER_DOLL.possessiveAdjective": "她的",
  "MORIMENS_CHARACTER_DOLL.pronounObject": "她",
  "MORIMENS_CHARACTER_DOLL.pronounPossessive": "她的",
  "MORIMENS_CHARACTER_DOLL.pronounSubject": "她",
  "MORIMENS_CHARACTER_DOLL.selectMessage": "模板角色准备就绪。",
  "MORIMENS_CHARACTER_DOLL.title": "朵爾",
  "MORIMENS_CHARACTER_DOLL.titleObject": "朵爾",
  "MORIMENS_CHARACTER_DOLL.unlockText": "用[pink]{Prerequisite}[/pink]进行一局游戏来解锁这个角色。",
  "MORIMENS_CHARACTER_DOLL.victoryMessage": "模板验证完成。"
}
